{"trial_id": "b9b01cb35a8e4171a793ce53360a055a", "hyperparameters": {"space": [{"class_name": "Boolean", "config": {"name": "structured_data_block_1/normalize", "default": false, "conditions": []}}, {"class_name": "Boolean", "config": {"name": "structured_data_block_1/dense_block_1/use_batchnorm", "default": false, "conditions": []}}, {"class_name": "Choice", "config": {"name": "structured_data_block_1/dense_block_1/num_layers", "default": 2, "conditions": [], "values": [1, 2, 3], "ordered": true}}, {"class_name": "Choice", "config": {"name": "structured_data_block_1/dense_block_1/units_0", "default": 32, "conditions": [], "values": [16, 32, 64, 128, 256, 512, 1024], "ordered": true}}, {"class_name": "Choice", "config": {"name": "structured_data_block_1/dense_block_1/dropout", "default": 0.0, "conditions": [], "values": [0.0, 0.25, 0.5], "ordered": true}}, {"class_name": "Choice", "config": {"name": "structured_data_block_1/dense_block_1/units_1", "default": 32, "conditions": [], "values": [16, 32, 64, 128, 256, 512, 1024], "ordered": true}}, {"class_name": "Choice", "config": {"name": "classification_head_1/dropout", "default": 0, "conditions": [], "values": [0.0, 0.25, 0.5], "ordered": true}}, {"class_name": "Choice", "config": {"name": "optimizer", "default": "adam", "conditions": [], "values": ["adam", "sgd", "adam_weight_decay"], "ordered": false}}, {"class_name": "Choice", "config": {"name": "learning_rate", "default": 0.001, "conditions": [], "values": [0.1, 0.01, 0.001, 0.0001, 2e-05, 1e-05], "ordered": true}}, {"class_name": "Choice", "config": {"name": "structured_data_block_1/dense_block_1/units_2", "default": 32, "conditions": [], "values": [16, 32, 64, 128, 256, 512, 1024], "ordered": true}}], "values": {"structured_data_block_1/normalize": true, "structured_data_block_1/dense_block_1/use_batchnorm": false, "structured_data_block_1/dense_block_1/num_layers": 2, "structured_data_block_1/dense_block_1/units_0": 64, "structured_data_block_1/dense_block_1/dropout": 0, "structured_data_block_1/dense_block_1/units_1": 32, "classification_head_1/dropout": 0.0, "optimizer": "adam", "learning_rate": 0.001, "structured_data_block_1/dense_block_1/units_2": 1024}}, "metrics": {"metrics": {"loss": {"direction": "min", "observations": [{"value": [1.6090004444122314], "step": 0}, {"value": [1.4730533361434937], "step": 1}, {"value": [1.3551791906356812], "step": 2}, {"value": [1.2531476020812988], "step": 3}, {"value": [1.1629663705825806], "step": 4}, {"value": [1.0829920768737793], "step": 5}, {"value": [1.0098161697387695], "step": 6}, {"value": [0.9412587285041809], "step": 7}, {"value": [0.877663791179657], "step": 8}, {"value": [0.8203451037406921], "step": 9}, {"value": [0.7700769305229187], "step": 10}, {"value": [0.7257267832756042], "step": 11}, {"value": [0.6868303418159485], "step": 12}, {"value": [0.6526662111282349], "step": 13}, {"value": [0.6229453682899475], "step": 14}, {"value": [0.597429633140564], "step": 15}, {"value": [0.5755923390388489], "step": 16}, {"value": [0.5564371347427368], "step": 17}, {"value": [0.5395969152450562], "step": 18}, {"value": [0.5245558023452759], "step": 19}, {"value": [0.511203408241272], "step": 20}, {"value": [0.4993623197078705], "step": 21}, {"value": [0.4883398413658142], "step": 22}, {"value": [0.4782828688621521], "step": 23}, {"value": [0.4690777361392975], "step": 24}, {"value": [0.46067237854003906], "step": 25}, {"value": [0.4526558816432953], "step": 26}, {"value": [0.44504570960998535], "step": 27}, {"value": [0.4374980926513672], "step": 28}, {"value": [0.42990413308143616], "step": 29}, {"value": [0.4227946400642395], "step": 30}, {"value": [0.4162936210632324], "step": 31}, {"value": [0.4098885655403137], "step": 32}, {"value": [0.40386277437210083], "step": 33}, {"value": [0.3980766832828522], "step": 34}, {"value": [0.39258718490600586], "step": 35}, {"value": [0.38730818033218384], "step": 36}, {"value": [0.3820998966693878], "step": 37}, {"value": [0.3770861029624939], "step": 38}, {"value": [0.3721691966056824], "step": 39}, {"value": [0.3672943711280823], "step": 40}, {"value": [0.36264437437057495], "step": 41}, {"value": [0.3581520915031433], "step": 42}, {"value": [0.35374078154563904], "step": 43}, {"value": [0.3494488596916199], "step": 44}, {"value": [0.34521719813346863], "step": 45}, {"value": [0.34127241373062134], "step": 46}, {"value": [0.33739104866981506], "step": 47}, {"value": [0.3336423933506012], "step": 48}, {"value": [0.3299922049045563], "step": 49}, {"value": [0.3264348804950714], "step": 50}, {"value": [0.32301631569862366], "step": 51}, {"value": [0.31967487931251526], "step": 52}, {"value": [0.3165096640586853], "step": 53}, {"value": [0.3134142756462097], "step": 54}, {"value": [0.31038033962249756], "step": 55}, {"value": [0.3074524402618408], "step": 56}, {"value": [0.30459481477737427], "step": 57}, {"value": [0.3018345534801483], "step": 58}, {"value": [0.299116313457489], "step": 59}, {"value": [0.2964971661567688], "step": 60}, {"value": [0.29390040040016174], "step": 61}, {"value": [0.2913212776184082], "step": 62}, {"value": [0.28881439566612244], "step": 63}, {"value": [0.28638070821762085], "step": 64}, {"value": [0.2840333878993988], "step": 65}, {"value": [0.2817552983760834], "step": 66}, {"value": [0.2794942855834961], "step": 67}, {"value": [0.2772900462150574], "step": 68}, {"value": [0.27513155341148376], "step": 69}, {"value": [0.27299976348876953], "step": 70}, {"value": [0.27092990279197693], "step": 71}, {"value": [0.2688893675804138], "step": 72}, {"value": [0.2668525278568268], "step": 73}, {"value": [0.26487046480178833], "step": 74}, {"value": [0.26294034719467163], "step": 75}, {"value": [0.2610704004764557], "step": 76}, {"value": [0.2592311501502991], "step": 77}, {"value": [0.257392555475235], "step": 78}, {"value": [0.2556031048297882], "step": 79}, {"value": [0.25385889410972595], "step": 80}, {"value": [0.2521592676639557], "step": 81}, {"value": [0.25050249695777893], "step": 82}, {"value": [0.24886250495910645], "step": 83}, {"value": [0.24724027514457703], "step": 84}, {"value": [0.24564023315906525], "step": 85}, {"value": [0.24409151077270508], "step": 86}, {"value": [0.24254179000854492], "step": 87}, {"value": [0.24101531505584717], "step": 88}, {"value": [0.23952683806419373], "step": 89}, {"value": [0.23803552985191345], "step": 90}, {"value": [0.23662272095680237], "step": 91}, {"value": [0.23526009917259216], "step": 92}, {"value": [0.23390257358551025], "step": 93}, {"value": [0.23258419334888458], "step": 94}, {"value": [0.23128771781921387], "step": 95}, {"value": [0.2300596684217453], "step": 96}, {"value": [0.22885680198669434], "step": 97}, {"value": [0.2276553213596344], "step": 98}, {"value": [0.2264842689037323], "step": 99}, {"value": [0.2253221720457077], "step": 100}, {"value": [0.2241300642490387], "step": 101}, {"value": [0.22304487228393555], "step": 102}, {"value": [0.22191765904426575], "step": 103}, {"value": [0.2208859622478485], "step": 104}, {"value": [0.2198229283094406], "step": 105}, {"value": [0.21877820789813995], "step": 106}, {"value": [0.2177746742963791], "step": 107}, {"value": [0.21674957871437073], "step": 108}, {"value": [0.21575984358787537], "step": 109}, {"value": [0.21485209465026855], "step": 110}, {"value": [0.21384915709495544], "step": 111}, {"value": [0.2129095047712326], "step": 112}, {"value": [0.21201081573963165], "step": 113}, {"value": [0.2110888510942459], "step": 114}, {"value": [0.21017858386039734], "step": 115}, {"value": [0.2092304676771164], "step": 116}, {"value": [0.20832698047161102], "step": 117}, {"value": [0.20742562413215637], "step": 118}, {"value": [0.20658037066459656], "step": 119}, {"value": [0.20571598410606384], "step": 120}, {"value": [0.20486769080162048], "step": 121}, {"value": [0.20403316617012024], "step": 122}, {"value": [0.20323224365711212], "step": 123}, {"value": [0.20237252116203308], "step": 124}, {"value": [0.20157556235790253], "step": 125}, {"value": [0.2007979154586792], "step": 126}, {"value": [0.20006045699119568], "step": 127}]}, "accuracy": {"direction": "max", "observations": [{"value": [0.16875000298023224], "step": 0}, {"value": [0.4124999940395355], "step": 1}, {"value": [0.643750011920929], "step": 2}, {"value": [0.7124999761581421], "step": 3}, {"value": [0.7562500238418579], "step": 4}, {"value": [0.737500011920929], "step": 5}, {"value": [0.737500011920929], "step": 6}, {"value": [0.737500011920929], "step": 7}, {"value": [0.731249988079071], "step": 8}, {"value": [0.737500011920929], "step": 9}, {"value": [0.737500011920929], "step": 10}, {"value": [0.75], "step": 11}, {"value": [0.75], "step": 12}, {"value": [0.7562500238418579], "step": 13}, {"value": [0.7749999761581421], "step": 14}, {"value": [0.800000011920929], "step": 15}, {"value": [0.8062499761581421], "step": 16}, {"value": [0.8125], "step": 17}, {"value": [0.8187500238418579], "step": 18}, {"value": [0.824999988079071], "step": 19}, {"value": [0.831250011920929], "step": 20}, {"value": [0.8374999761581421], "step": 21}, {"value": [0.8374999761581421], "step": 22}, {"value": [0.84375], "step": 23}, {"value": [0.84375], "step": 24}, {"value": [0.84375], "step": 25}, {"value": [0.8500000238418579], "step": 26}, {"value": [0.862500011920929], "step": 27}, {"value": [0.862500011920929], "step": 28}, {"value": [0.862500011920929], "step": 29}, {"value": [0.862500011920929], "step": 30}, {"value": [0.8687499761581421], "step": 31}, {"value": [0.8687499761581421], "step": 32}, {"value": [0.8687499761581421], "step": 33}, {"value": [0.875], "step": 34}, {"value": [0.875], "step": 35}, {"value": [0.8687499761581421], "step": 36}, {"value": [0.8687499761581421], "step": 37}, {"value": [0.8687499761581421], "step": 38}, {"value": [0.8687499761581421], "step": 39}, {"value": [0.875], "step": 40}, {"value": [0.8812500238418579], "step": 41}, {"value": [0.8812500238418579], "step": 42}, {"value": [0.8812500238418579], "step": 43}, {"value": [0.8812500238418579], "step": 44}, {"value": [0.8812500238418579], "step": 45}, {"value": [0.8812500238418579], "step": 46}, {"value": [0.8812500238418579], "step": 47}, {"value": [0.8812500238418579], "step": 48}, {"value": [0.8812500238418579], "step": 49}, {"value": [0.8812500238418579], "step": 50}, {"value": [0.887499988079071], "step": 51}, {"value": [0.887499988079071], "step": 52}, {"value": [0.893750011920929], "step": 53}, {"value": [0.893750011920929], "step": 54}, {"value": [0.893750011920929], "step": 55}, {"value": [0.893750011920929], "step": 56}, {"value": [0.893750011920929], "step": 57}, {"value": [0.893750011920929], "step": 58}, {"value": [0.893750011920929], "step": 59}, {"value": [0.893750011920929], "step": 60}, {"value": [0.893750011920929], "step": 61}, {"value": [0.8999999761581421], "step": 62}, {"value": [0.8999999761581421], "step": 63}, {"value": [0.8999999761581421], "step": 64}, {"value": [0.8999999761581421], "step": 65}, {"value": [0.90625], "step": 66}, {"value": [0.90625], "step": 67}, {"value": [0.90625], "step": 68}, {"value": [0.90625], "step": 69}, {"value": [0.90625], "step": 70}, {"value": [0.90625], "step": 71}, {"value": [0.9125000238418579], "step": 72}, {"value": [0.90625], "step": 73}, {"value": [0.918749988079071], "step": 74}, {"value": [0.918749988079071], "step": 75}, {"value": [0.918749988079071], "step": 76}, {"value": [0.918749988079071], "step": 77}, {"value": [0.918749988079071], "step": 78}, {"value": [0.918749988079071], "step": 79}, {"value": [0.918749988079071], "step": 80}, {"value": [0.918749988079071], "step": 81}, {"value": [0.918749988079071], "step": 82}, {"value": [0.918749988079071], "step": 83}, {"value": [0.918749988079071], "step": 84}, {"value": [0.918749988079071], "step": 85}, {"value": [0.918749988079071], "step": 86}, {"value": [0.918749988079071], "step": 87}, {"value": [0.918749988079071], "step": 88}, {"value": [0.918749988079071], "step": 89}, {"value": [0.918749988079071], "step": 90}, {"value": [0.918749988079071], "step": 91}, {"value": [0.918749988079071], "step": 92}, {"value": [0.918749988079071], "step": 93}, {"value": [0.918749988079071], "step": 94}, {"value": [0.918749988079071], "step": 95}, {"value": [0.918749988079071], "step": 96}, {"value": [0.918749988079071], "step": 97}, {"value": [0.918749988079071], "step": 98}, {"value": [0.918749988079071], "step": 99}, {"value": [0.918749988079071], "step": 100}, {"value": [0.918749988079071], "step": 101}, {"value": [0.918749988079071], "step": 102}, {"value": [0.925000011920929], "step": 103}, {"value": [0.925000011920929], "step": 104}, {"value": [0.925000011920929], "step": 105}, {"value": [0.925000011920929], "step": 106}, {"value": [0.925000011920929], "step": 107}, {"value": [0.925000011920929], "step": 108}, {"value": [0.925000011920929], "step": 109}, {"value": [0.925000011920929], "step": 110}, {"value": [0.925000011920929], "step": 111}, {"value": [0.925000011920929], "step": 112}, {"value": [0.9312499761581421], "step": 113}, {"value": [0.9312499761581421], "step": 114}, {"value": [0.9312499761581421], "step": 115}, {"value": [0.9312499761581421], "step": 116}, {"value": [0.9312499761581421], "step": 117}, {"value": [0.9312499761581421], "step": 118}, {"value": [0.9312499761581421], "step": 119}, {"value": [0.9312499761581421], "step": 120}, {"value": [0.9312499761581421], "step": 121}, {"value": [0.9312499761581421], "step": 122}, {"value": [0.9312499761581421], "step": 123}, {"value": [0.9312499761581421], "step": 124}, {"value": [0.9312499761581421], "step": 125}, {"value": [0.9312499761581421], "step": 126}, {"value": [0.9312499761581421], "step": 127}]}, "val_loss": {"direction": "min", "observations": [{"value": [1.5180062055587769], "step": 0}, {"value": [1.4160802364349365], "step": 1}, {"value": [1.3289724588394165], "step": 2}, {"value": [1.2514002323150635], "step": 3}, {"value": [1.180645227432251], "step": 4}, {"value": [1.1153414249420166], "step": 5}, {"value": [1.0548574924468994], "step": 6}, {"value": [0.9963682889938354], "step": 7}, {"value": [0.9419422745704651], "step": 8}, {"value": [0.8935116529464722], "step": 9}, {"value": [0.8520171642303467], "step": 10}, {"value": [0.8159825205802917], "step": 11}, {"value": [0.7845363020896912], "step": 12}, {"value": [0.7570192813873291], "step": 13}, {"value": [0.7324944734573364], "step": 14}, {"value": [0.7109572887420654], "step": 15}, {"value": [0.6919432282447815], "step": 16}, {"value": [0.6754647493362427], "step": 17}, {"value": [0.6608154773712158], "step": 18}, {"value": [0.6479285955429077], "step": 19}, {"value": [0.6364599466323853], "step": 20}, {"value": [0.625970184803009], "step": 21}, {"value": [0.6162316799163818], "step": 22}, {"value": [0.6072567701339722], "step": 23}, {"value": [0.5990315675735474], "step": 24}, {"value": [0.5914345383644104], "step": 25}, {"value": [0.5840888619422913], "step": 26}, {"value": [0.5769220590591431], "step": 27}, {"value": [0.57024085521698], "step": 28}, {"value": [0.5623615384101868], "step": 29}, {"value": [0.5549803972244263], "step": 30}, {"value": [0.5490764379501343], "step": 31}, {"value": [0.5446702837944031], "step": 32}, {"value": [0.5409176349639893], "step": 33}, {"value": [0.5374448895454407], "step": 34}, {"value": [0.533850908279419], "step": 35}, {"value": [0.5301898121833801], "step": 36}, {"value": [0.5267304182052612], "step": 37}, {"value": [0.5232188701629639], "step": 38}, {"value": [0.5197838544845581], "step": 39}, {"value": [0.5167093276977539], "step": 40}, {"value": [0.5135963559150696], "step": 41}, {"value": [0.510543942451477], "step": 42}, {"value": [0.5075379610061646], "step": 43}, {"value": [0.5046594142913818], "step": 44}, {"value": [0.502080500125885], "step": 45}, {"value": [0.49952250719070435], "step": 46}, {"value": [0.49714404344558716], "step": 47}, {"value": [0.49482887983322144], "step": 48}, {"value": [0.4927363097667694], "step": 49}, {"value": [0.49072569608688354], "step": 50}, {"value": [0.48868095874786377], "step": 51}, {"value": [0.486470103263855], "step": 52}, {"value": [0.484316885471344], "step": 53}, {"value": [0.48237866163253784], "step": 54}, {"value": [0.4807025194168091], "step": 55}, {"value": [0.4790525436401367], "step": 56}, {"value": [0.4774886965751648], "step": 57}, {"value": [0.47571229934692383], "step": 58}, {"value": [0.4740716516971588], "step": 59}, {"value": [0.472455233335495], "step": 60}, {"value": [0.4708724021911621], "step": 61}, {"value": [0.4693669080734253], "step": 62}, {"value": [0.46779683232307434], "step": 63}, {"value": [0.466399222612381], "step": 64}, {"value": [0.4649062752723694], "step": 65}, {"value": [0.46319296956062317], "step": 66}, {"value": [0.4615488350391388], "step": 67}, {"value": [0.45999473333358765], "step": 68}, {"value": [0.4588682949542999], "step": 69}, {"value": [0.45767858624458313], "step": 70}, {"value": [0.4563511610031128], "step": 71}, {"value": [0.45513227581977844], "step": 72}, {"value": [0.45401227474212646], "step": 73}, {"value": [0.45273077487945557], "step": 74}, {"value": [0.4515170454978943], "step": 75}, {"value": [0.45024949312210083], "step": 76}, {"value": [0.44893261790275574], "step": 77}, {"value": [0.4477938115596771], "step": 78}, {"value": [0.4465410113334656], "step": 79}, {"value": [0.44513314962387085], "step": 80}, {"value": [0.44416242837905884], "step": 81}, {"value": [0.44321542978286743], "step": 82}, {"value": [0.4420788884162903], "step": 83}, {"value": [0.4408758878707886], "step": 84}, {"value": [0.43987295031547546], "step": 85}, {"value": [0.4388296902179718], "step": 86}, {"value": [0.43804025650024414], "step": 87}, {"value": [0.437269002199173], "step": 88}, {"value": [0.4364205002784729], "step": 89}, {"value": [0.4355192482471466], "step": 90}, {"value": [0.4347008466720581], "step": 91}, {"value": [0.4339649975299835], "step": 92}, {"value": [0.4334627687931061], "step": 93}, {"value": [0.433025985956192], "step": 94}, {"value": [0.4325641393661499], "step": 95}, {"value": [0.4320923388004303], "step": 96}, {"value": [0.4314782917499542], "step": 97}, {"value": [0.4308452606201172], "step": 98}, {"value": [0.43031805753707886], "step": 99}, {"value": [0.4298537075519562], "step": 100}, {"value": [0.4292862117290497], "step": 101}, {"value": [0.4287722408771515], "step": 102}, {"value": [0.42839229106903076], "step": 103}, {"value": [0.42793047428131104], "step": 104}, {"value": [0.42795494198799133], "step": 105}, {"value": [0.4274827241897583], "step": 106}, {"value": [0.42706161737442017], "step": 107}, {"value": [0.42705172300338745], "step": 108}, {"value": [0.4266643524169922], "step": 109}, {"value": [0.4260781705379486], "step": 110}, {"value": [0.4261496663093567], "step": 111}, {"value": [0.42648786306381226], "step": 112}, {"value": [0.42608925700187683], "step": 113}, {"value": [0.4256415069103241], "step": 114}, {"value": [0.4252431094646454], "step": 115}, {"value": [0.4251422584056854], "step": 116}, {"value": [0.4249165654182434], "step": 117}, {"value": [0.42522794008255005], "step": 118}, {"value": [0.42509809136390686], "step": 119}, {"value": [0.42492997646331787], "step": 120}, {"value": [0.42514675855636597], "step": 121}, {"value": [0.4253252148628235], "step": 122}, {"value": [0.42521968483924866], "step": 123}, {"value": [0.42557621002197266], "step": 124}, {"value": [0.4261535406112671], "step": 125}, {"value": [0.42673009634017944], "step": 126}, {"value": [0.426541805267334], "step": 127}]}, "val_accuracy": {"direction": "max", "observations": [{"value": [0.3076923191547394], "step": 0}, {"value": [0.42307692766189575], "step": 1}, {"value": [0.5384615659713745], "step": 2}, {"value": [0.5384615659713745], "step": 3}, {"value": [0.5769230723381042], "step": 4}, {"value": [0.5769230723381042], "step": 5}, {"value": [0.5769230723381042], "step": 6}, {"value": [0.5769230723381042], "step": 7}, {"value": [0.5769230723381042], "step": 8}, {"value": [0.5769230723381042], "step": 9}, {"value": [0.5769230723381042], "step": 10}, {"value": [0.5769230723381042], "step": 11}, {"value": [0.5769230723381042], "step": 12}, {"value": [0.6153846383094788], "step": 13}, {"value": [0.6153846383094788], "step": 14}, {"value": [0.6153846383094788], "step": 15}, {"value": [0.6538461446762085], "step": 16}, {"value": [0.692307710647583], "step": 17}, {"value": [0.692307710647583], "step": 18}, {"value": [0.692307710647583], "step": 19}, {"value": [0.692307710647583], "step": 20}, {"value": [0.692307710647583], "step": 21}, {"value": [0.7307692170143127], "step": 22}, {"value": [0.7307692170143127], "step": 23}, {"value": [0.7307692170143127], "step": 24}, {"value": [0.7307692170143127], "step": 25}, {"value": [0.7307692170143127], "step": 26}, {"value": [0.7307692170143127], "step": 27}, {"value": [0.7307692170143127], "step": 28}, {"value": [0.7307692170143127], "step": 29}, {"value": [0.7307692170143127], "step": 30}, {"value": [0.7307692170143127], "step": 31}, {"value": [0.7307692170143127], "step": 32}, {"value": [0.7307692170143127], "step": 33}, {"value": [0.7307692170143127], "step": 34}, {"value": [0.7307692170143127], "step": 35}, {"value": [0.7307692170143127], "step": 36}, {"value": [0.7307692170143127], "step": 37}, {"value": [0.7307692170143127], "step": 38}, {"value": [0.7307692170143127], "step": 39}, {"value": [0.7692307829856873], "step": 40}, {"value": [0.7692307829856873], "step": 41}, {"value": [0.7692307829856873], "step": 42}, {"value": [0.7692307829856873], "step": 43}, {"value": [0.7692307829856873], "step": 44}, {"value": [0.7692307829856873], "step": 45}, {"value": [0.7692307829856873], "step": 46}, {"value": [0.7692307829856873], "step": 47}, {"value": [0.7692307829856873], "step": 48}, {"value": [0.7692307829856873], "step": 49}, {"value": [0.7692307829856873], "step": 50}, {"value": [0.7692307829856873], "step": 51}, {"value": [0.7692307829856873], "step": 52}, {"value": [0.7692307829856873], "step": 53}, {"value": [0.7692307829856873], "step": 54}, {"value": [0.7692307829856873], "step": 55}, {"value": [0.7692307829856873], "step": 56}, {"value": [0.7692307829856873], "step": 57}, {"value": [0.7692307829856873], "step": 58}, {"value": [0.7692307829856873], "step": 59}, {"value": [0.7692307829856873], "step": 60}, {"value": [0.7692307829856873], "step": 61}, {"value": [0.7692307829856873], "step": 62}, {"value": [0.7692307829856873], "step": 63}, {"value": [0.7692307829856873], "step": 64}, {"value": [0.7692307829856873], "step": 65}, {"value": [0.7692307829856873], "step": 66}, {"value": [0.7692307829856873], "step": 67}, {"value": [0.7692307829856873], "step": 68}, {"value": [0.7692307829856873], "step": 69}, {"value": [0.7692307829856873], "step": 70}, {"value": [0.7692307829856873], "step": 71}, {"value": [0.7692307829856873], "step": 72}, {"value": [0.7692307829856873], "step": 73}, {"value": [0.807692289352417], "step": 74}, {"value": [0.807692289352417], "step": 75}, {"value": [0.807692289352417], "step": 76}, {"value": [0.7692307829856873], "step": 77}, {"value": [0.7692307829856873], "step": 78}, {"value": [0.7692307829856873], "step": 79}, {"value": [0.7692307829856873], "step": 80}, {"value": [0.7692307829856873], "step": 81}, {"value": [0.7692307829856873], "step": 82}, {"value": [0.7692307829856873], "step": 83}, {"value": [0.7692307829856873], "step": 84}, {"value": [0.7692307829856873], "step": 85}, {"value": [0.7692307829856873], "step": 86}, {"value": [0.7692307829856873], "step": 87}, {"value": [0.7692307829856873], "step": 88}, {"value": [0.7692307829856873], "step": 89}, {"value": [0.7692307829856873], "step": 90}, {"value": [0.7692307829856873], "step": 91}, {"value": [0.7692307829856873], "step": 92}, {"value": [0.7692307829856873], "step": 93}, {"value": [0.7692307829856873], "step": 94}, {"value": [0.807692289352417], "step": 95}, {"value": [0.807692289352417], "step": 96}, {"value": [0.807692289352417], "step": 97}, {"value": [0.807692289352417], "step": 98}, {"value": [0.807692289352417], "step": 99}, {"value": [0.807692289352417], "step": 100}, {"value": [0.807692289352417], "step": 101}, {"value": [0.807692289352417], "step": 102}, {"value": [0.807692289352417], "step": 103}, {"value": [0.807692289352417], "step": 104}, {"value": [0.807692289352417], "step": 105}, {"value": [0.807692289352417], "step": 106}, {"value": [0.807692289352417], "step": 107}, {"value": [0.807692289352417], "step": 108}, {"value": [0.807692289352417], "step": 109}, {"value": [0.807692289352417], "step": 110}, {"value": [0.807692289352417], "step": 111}, {"value": [0.807692289352417], "step": 112}, {"value": [0.807692289352417], "step": 113}, {"value": [0.807692289352417], "step": 114}, {"value": [0.807692289352417], "step": 115}, {"value": [0.807692289352417], "step": 116}, {"value": [0.807692289352417], "step": 117}, {"value": [0.807692289352417], "step": 118}, {"value": [0.807692289352417], "step": 119}, {"value": [0.807692289352417], "step": 120}, {"value": [0.807692289352417], "step": 121}, {"value": [0.807692289352417], "step": 122}, {"value": [0.807692289352417], "step": 123}, {"value": [0.807692289352417], "step": 124}, {"value": [0.807692289352417], "step": 125}, {"value": [0.807692289352417], "step": 126}, {"value": [0.807692289352417], "step": 127}]}}}, "score": 0.807692289352417, "best_step": 74, "status": "COMPLETED"}